joserfc/__init__.py
joserfc/_keys.py
joserfc/errors.py
joserfc/jwa.py
joserfc/jwe.py
joserfc/jwk.py
joserfc/jws.py
joserfc/jwt.py
joserfc/py.typed
joserfc/registry.py
joserfc/util.py
joserfc/_rfc7515/__init__.py
joserfc/_rfc7515/compact.py
joserfc/_rfc7515/json.py
joserfc/_rfc7515/model.py
joserfc/_rfc7515/registry.py
joserfc/_rfc7515/types.py
joserfc/_rfc7516/__init__.py
joserfc/_rfc7516/compact.py
joserfc/_rfc7516/json.py
joserfc/_rfc7516/message.py
joserfc/_rfc7516/models.py
joserfc/_rfc7516/registry.py
joserfc/_rfc7516/types.py
joserfc/_rfc7517/__init__.py
joserfc/_rfc7517/models.py
joserfc/_rfc7517/pem.py
joserfc/_rfc7517/types.py
joserfc/_rfc7518/__init__.py
joserfc/_rfc7518/derive_key.py
joserfc/_rfc7518/ec_key.py
joserfc/_rfc7518/jwe_algs.py
joserfc/_rfc7518/jwe_encs.py
joserfc/_rfc7518/jwe_zips.py
joserfc/_rfc7518/jws_algs.py
joserfc/_rfc7518/oct_key.py
joserfc/_rfc7518/rsa_key.py
joserfc/_rfc7518/util.py
joserfc/_rfc7519/__init__.py
joserfc/_rfc7519/claims.py
joserfc/_rfc7519/security.py
joserfc/_rfc7638/__init__.py
joserfc/_rfc7797/__init__.py
joserfc/_rfc7797/compact.py
joserfc/_rfc7797/json.py
joserfc/_rfc7797/util.py
joserfc/_rfc8037/__init__.py
joserfc/_rfc8037/jws_eddsa.py
joserfc/_rfc8037/okp_key.py
joserfc/_rfc8812/__init__.py
joserfc/_rfc9278/__init__.py
joserfc/_rfc9864/__init__.py
joserfc/_rfc9864/jws_eddsa.py
joserfc/drafts/__init__.py
joserfc/drafts/jwe_chacha20.py
joserfc/drafts/jwe_ecdh_1pu.py
joserfc-1.6.0.dist-info/licenses/LICENSE
joserfc-1.6.0.dist-info/METADATA
joserfc-1.6.0.dist-info/WHEEL
joserfc-1.6.0.dist-info/top_level.txt
joserfc-1.6.0.dist-info/RECORD
