Metadata-Version: 2.4
Name: joserfc
Version: 1.6.0
Summary: The ultimate Python library for JOSE RFCs, including JWS, JWE, JWK, JWA, JWT
Author-email: Hsiaoming Yang <me@lepture.com>
License: BSD-3-Clause
Project-URL: Documentation, https://jose.authlib.org/
Project-URL: Source, https://github.com/authlib/joserfc
Project-URL: Funding, https://github.com/sponsors/authlib
Project-URL: Blog, https://blog.authlib.org/
Classifier: Development Status :: 5 - Production/Stable
Classifier: Environment :: Console
Classifier: Environment :: Web Environment
Classifier: Intended Audience :: Developers
Classifier: License :: OSI Approved :: BSD License
Classifier: Operating System :: OS Independent
Classifier: Programming Language :: Python
Classifier: Programming Language :: Python :: 3
Classifier: Programming Language :: Python :: 3.9
Classifier: Programming Language :: Python :: 3.10
Classifier: Programming Language :: Python :: 3.11
Classifier: Programming Language :: Python :: 3.12
Classifier: Programming Language :: Python :: 3.13
Classifier: Programming Language :: Python :: 3.14
Classifier: Programming Language :: Python :: Implementation :: CPython
Classifier: Programming Language :: Python :: Implementation :: PyPy
Classifier: Topic :: Security
Classifier: Topic :: Security :: Cryptography
Requires-Python: >=3.9
License-File: LICENSE
Requires-Dist: cryptography>=45.0.1
Provides-Extra: drafts
Requires-Dist: pycryptodome; extra == "drafts"
Dynamic: license-file
